{
  "main": {
    "id": "6f2e00cb3f1e01e8",
    "type": "split",
    "children": [
      {
        "id": "68b5b1153b5047a7",
        "type": "tabs",
        "children": [
          {
            "id": "d6c5fb8c18675b10",
            "type": "leaf",
            "state": {
              "type": "markdown",
              "state": {
                "file": "doc/misc shit.md",
                "mode": "source",
                "source": false
              },
              "icon": "lucide-file",
              "title": "misc shit"
            }
          },
          {
            "id": "0467a2410ef122c9",
            "type": "leaf",
            "state": {
              "type": "kanban",
              "state": {
                "file": "doc/development todos.md",
                "kanbanViewState": {
                  "kanban-plugin": "board",
                  "list-collapse": [
                    false,
                    false,
                    false
                  ]
                }
              },
              "icon": "lucide-trello",
              "title": "development todos"
            }
          },
          {
            "id": "a4940339f26bada4",
            "type": "leaf",
            "state": {
              "type": "kanban",
              "state": {
                "file": "doc/research kanban.md",
                "kanbanViewState": {
                  "kanban-plugin": "board",
                  "list-collapse": [
                    false,
                    false,
                    false,
                    false
                  ]
                }
              },
              "icon": "lucide-trello",
              "title": "research kanban"
            }
          },
          {
            "id": "bf840b46f3fa0349",
            "type": "leaf",
            "state": {
              "type": "kanban",
              "state": {
                "file": "doc/task board.md",
                "kanbanViewState": {
                  "kanban-plugin": "board",
                  "list-collapse": [
                    false,
                    false,
                    false
                  ]
                }
              },
              "icon": "lucide-trello",
              "title": "task board"
            }
          }
        ],
        "currentTab": 1
      }
    ],
    "direction": "vertical"
  },
  "left": {
    "id": "249b73ee281336eb",
    "type": "split",
    "children": [
      {
        "id": "7b8d25e9ebd06c4c",
        "type": "tabs",
        "children": [
          {
            "id": "60e8ac5952277439",
            "type": "leaf",
            "state": {
              "type": "file-explorer",
              "state": {
                "sortOrder": "alphabetical",
                "autoReveal": false
              },
              "icon": "lucide-folder-closed",
              "title": "Files"
            }
          },
          {
            "id": "4a3fddea6d248c8d",
            "type": "leaf",
            "state": {
              "type": "search",
              "state": {
                "query": "",
                "matchingCase": false,
                "explainSearch": false,
                "collapseAll": false,
                "extraContext": false,
                "sortOrder": "alphabetical"
              },
              "icon": "lucide-search",
              "title": "Search"
            }
          },
          {
            "id": "b03750af2c6efe6b",
            "type": "leaf",
            "state": {
              "type": "bookmarks",
              "state": {},
              "icon": "lucide-bookmark",
              "title": "Bookmarks"
            }
          }
        ]
      }
    ],
    "direction": "horizontal",
    "width": 300
  },
  "right": {
    "id": "f9232ef4b6037c5b",
    "type": "split",
    "children": [
      {
        "id": "c19c91237918d0d6",
        "type": "tabs",
        "children": [
          {
            "id": "4976d9535bf24ae1",
            "type": "leaf",
            "state": {
              "type": "backlink",
              "state": {
                "collapseAll": false,
                "extraContext": false,
                "sortOrder": "alphabetical",
                "showSearch": false,
                "searchQuery": "",
                "backlinkCollapsed": false,
                "unlinkedCollapsed": true
              },
              "icon": "links-coming-in",
              "title": "Backlinks"
            }
          },
          {
            "id": "176dbdcb719c5b0e",
            "type": "leaf",
            "state": {
              "type": "outgoing-link",
              "state": {
                "linksCollapsed": false,
                "unlinkedCollapsed": true
              },
              "icon": "links-going-out",
              "title": "Outgoing links"
            }
          },
          {
            "id": "98b5c16960b2c39d",
            "type": "leaf",
            "state": {
              "type": "tag",
              "state": {
                "sortOrder": "frequency",
                "useHierarchy": true,
                "showSearch": false,
                "searchQuery": ""
              },
              "icon": "lucide-tags",
              "title": "Tags"
            }
          },
          {
            "id": "1dbe388f0a407107",
            "type": "leaf",
            "state": {
              "type": "outline",
              "state": {
                "followCursor": false,
                "showSearch": false,
                "searchQuery": ""
              },
              "icon": "lucide-list",
              "title": "Outline"
            }
          }
        ]
      }
    ],
    "direction": "horizontal",
    "width": 300,
    "collapsed": true
  },
  "left-ribbon": {
    "hiddenItems": {
      "switcher:Open quick switcher": false,
      "graph:Open graph view": false,
      "canvas:Create new canvas": false,
      "daily-notes:Open today's daily note": false,
      "templates:Insert template": false,
      "command-palette:Open command palette": false,
      "bases:Create new base": false,
      "obsidian-kanban:Create new board": false
    }
  },
  "active": "0467a2410ef122c9",
  "lastOpenFiles": [
    "res/tesselations.blend@",
    "out/benchmark_11_11_2025 13.19.06.6416243.csv",
    "out/benchmark_11_11_2025 13.18.55.3803199.csv",
    "out/benchmark_11_11_2025 13.18.44.6764861.csv",
    "out/benchmark_11_11_2025 13.18.17.6704488.csv",
    "x64/Release/mtvt.tlog/link.read.29.tlog",
    "x64/Release/mtvt.tlog/link-cvtres.write.1.tlog",
    "x64/Release/mtvt.tlog/link-cvtres.read.1.tlog",
    "x64/Release/mtvt.tlog/link-rc.write.1.tlog",
    "x64/Release/mtvt.tlog/link-rc.read.1.tlog",
    "x64/Release/MTVT.obj",
    "doc/task board.md",
    "doc/research kanban.md",
    "doc/development todos.md",
    "doc/research notes/A new tetrahedral tessellation scheme for isosurface generation (1998).md",
    "doc/research notes/amc crack problem.png",
    "doc/research notes/Marching Cubes (1987).md",
    "doc/research notes/Regularised marching tetrahedra (1999).md",
    "doc/research notes/miscellaneous notes.md",
    "doc/questionnaire template.md",
    "doc/img/irregular tetrahedral refinement.png",
    "doc/ethics/Pasted image 20251009125842.png",
    "doc/img/mutual tesselation.png",
    "doc/img/mt-5 abiguity.png",
    "doc/misc shit.md",
    "doc/img/regular tetrahedral refinement.png",
    "doc/lit review template.md",
    "doc/lit review template.md",
    "doc/merging reductions.md",
    "doc/Costen, Cassette - c025180n - Games Technology and Programming Development Thread - Digital Academy Forum_files/spacer.png",
    "doc/Costen, Cassette - c025180n - Games Technology and Programming Development Thread - Digital Academy Forum_files/simplecubiclattice.png.ff7358c464aa56aff4fec803f645a9d9.png",
    "doc/Costen, Cassette - c025180n - Games Technology and Programming Development Thread - Digital Academy Forum_files/react_like.png",
    "doc/Costen, Cassette - c025180n - Games Technology and Programming Development Thread - Digital Academy Forum_files/image.thumb.png.ee5f7ac07bcc2a99730aa9cb8cd57dcd.png",
    "doc/research notes.md",
    "Untitled.canvas",
    "2025-10-29.md",
    "doc/research notes/Adaptive marching cubes 1995.md",
    "doc/sample point and edge counting.md",
    "doc/kanban task board.md"
  ]
}